CHANGES.md
MANIFEST.in
README.md
UNLICENSE
setup.cfg
setup.py
src/pyramid_assetgen/__init__.py
src/pyramid_assetgen.egg-info/PKG-INFO
src/pyramid_assetgen.egg-info/SOURCES.txt
src/pyramid_assetgen.egg-info/dependency_links.txt
src/pyramid_assetgen.egg-info/not-zip-safe
src/pyramid_assetgen.egg-info/requires.txt
src/pyramid_assetgen.egg-info/top_level.txt
src/pyramid_assetgen/coffee/assetgen.coffee
src/pyramid_assetgen/templates/script_tag.mako
src/pyramid_assetgen/tests/__init__.py