Metadata-Version: 1.0
Name: pyramid-assetgen
Version: 0.5.4
Summary: Integrate Assetgen with the Pyramid framework.
Home-page: http://github.com/thruflo/pyramid_assetgen
Author: James Arthur
Author-email: username: thruflo, domain: gmail.com
License: This is free and unencumbered software released into the public domain.
Platform: UNKNOWN
Classifier: Development Status :: 4 - Beta
Classifier: Environment :: Web Environment
Classifier: Intended Audience :: Developers
Classifier: License :: Public Domain
Classifier: Natural Language :: English
Classifier: Operating System :: OS Independent
Classifier: Programming Language :: Python
Classifier: Programming Language :: Python :: 2.6
Classifier: Programming Language :: Python :: 2.7
Classifier: Programming Language :: Python :: 3
Classifier: Programming Language :: Python :: 3.2
Classifier: Framework :: Pylons
Classifier: Topic :: Internet :: WWW/HTTP
Classifier: Topic :: Internet :: WWW/HTTP :: WSGI
Classifier: Topic :: Software Development :: Libraries :: Python Modules
